src/app/application.py
src/app/device_registry.py
src/app/logger.py
src/app/main_window.py
src/app/menu_bar.py
src/app/stylesheet.qss
src/app/widget_registry.py
src/devices/reflex_v2.py
src/drivers/usb_hid.py
src/widgets/log_viewer.py
src/widgets/pad_interface.py
reflex_nexus-0.0.22.dist-info/LICENSE
reflex_nexus-0.0.22.dist-info/METADATA
reflex_nexus-0.0.22.dist-info/WHEEL
reflex_nexus-0.0.22.dist-info/entry_points.txt
reflex_nexus-0.0.22.dist-info/RECORD
