Metadata-Version: 2.1
Name: reflex-nexus
Version: 0.0.22
Summary: RE:Flex Nexus - Universal Dance Pad Utilities
Home-page: https://reflex.dance
License: MIT
Author: Brittany Barrett
Author-email: brittany.l.barrett@gmail.com
Requires-Python: >=3.10,<3.11
Classifier: License :: OSI Approved :: MIT License
Classifier: Programming Language :: Python :: 3
Classifier: Programming Language :: Python :: 3.10
Requires-Dist: PySide6
Requires-Dist: QtAwesome
Requires-Dist: libusb_package
Requires-Dist: pyqtdarktheme
Requires-Dist: pyusb
Project-URL: Documentation, https://reflex-nexus.readthedocs.io
Project-URL: Repository, https://github.com/ReflexCreations/Nexus
